tfpde/__init__.py
tfpde/boundary_conditions.py
tfpde/main.py
tfpde/network.py
tfpde/network_tf_module.py
tfpde/options.py
tfpde/pde.py
tfpde/plotter.py
tfpde/qnw.py
tfpde/sampler.py
tfpde/training_ground.py
tf_pde-0.7.dev0.dist-info/METADATA
tf_pde-0.7.dev0.dist-info/WHEEL
tf_pde-0.7.dev0.dist-info/top_level.txt
tf_pde-0.7.dev0.dist-info/RECORD
