Metadata-Version: 2.1
Name: tf-pde
Version: 0.7.dev0
Summary: Deep learning library for solving partial differential equations
Home-page: https://github.com/gitvicky/tf-pde
Author: Vignesh Gopakumar
Author-email: vignesh7g@gmail.com
License: MIT
Platform: UNKNOWN
Requires-Dist: numpy (==1.18.5)
Requires-Dist: matplotlib (==3.2.1)
Requires-Dist: scipy (==1.4.1)
Requires-Dist: sympy (==1.6)
Requires-Dist: tensorflow (==2.2.0)
Requires-Dist: tensorflow-probability (==0.10.0)
Requires-Dist: pydoe (==0.3.8)
Requires-Dist: cloudpickle (==1.4.1)
